codeforcespy/__init__.py
codeforcespy/base.py
codeforcespy/clients.py
codeforcespy/errors.py
codeforcespy/processors.py
codeforcespy/abc/__init__.py
codeforcespy/abc/cobjects.py
codeforcespy/abc/endpoints.py
codeforcespy/abc/interactions.py
codeforcespy/abc/objects.py
codeforcespy/abc/protocols.py
codeforcespy/features/__init__.py
codeforcespy/features/blog.py
codeforcespy/features/contest.py
codeforcespy/features/mixin_base.py
codeforcespy/features/problemset.py
codeforcespy/features/recent.py
codeforcespy/features/user.py
codeforcespy-1.2.1.dist-info/licenses/LICENSE
codeforcespy-1.2.1.dist-info/METADATA
codeforcespy-1.2.1.dist-info/WHEEL
codeforcespy-1.2.1.dist-info/top_level.txt
codeforcespy-1.2.1.dist-info/RECORD
