Metadata-Version: 2.4
Name: codeforcespy
Version: 1.2.1
Summary: A high-performance and type-safe Python library for seamless interaction with the Codeforces API. Supports both asynchronous and synchronous client handlers, enabling developers to choose the best approach for their needs.
Home-page: https://github.com/xsyncio/codeforcespy
Author: Xsyncio
Project-URL: Bug Tracker, https://github.com/xsyncio/codeforcespy/issues
Project-URL: Documentation, https://github.com/xsyncio/codeforcespy
Project-URL: Source, https://github.com/xsyncio/codeforcespy
Keywords: python,codeforces,api,wrapper,async,sync,type-safe,competitive-programming
Classifier: Development Status :: 5 - Production/Stable
Classifier: Intended Audience :: Developers
Classifier: Topic :: Software Development :: Libraries
Classifier: License :: OSI Approved :: GNU General Public License v3 (GPLv3)
Classifier: Programming Language :: Python :: 3
Classifier: Programming Language :: Python :: 3.9
Classifier: Programming Language :: Python :: 3.10
Classifier: Programming Language :: Python :: 3.11
Classifier: Programming Language :: Python :: 3.12
Classifier: Programming Language :: Python :: 3.13
Classifier: Operating System :: OS Independent
Classifier: Typing :: Typed
Requires-Python: >=3.9
License-File: LICENSE
Requires-Dist: httpx>=0.23.0
Requires-Dist: msgspec>=0.18.0
Provides-Extra: dev
Requires-Dist: ruff; extra == "dev"
Requires-Dist: pytest; extra == "dev"
Requires-Dist: mypy; extra == "dev"
Requires-Dist: basedpyright; extra == "dev"
Requires-Dist: respx; extra == "dev"
Requires-Dist: build; extra == "dev"
Dynamic: author
Dynamic: classifier
Dynamic: description
Dynamic: description-content-type
Dynamic: home-page
Dynamic: keywords
Dynamic: license-file
Dynamic: project-url
Dynamic: provides-extra
Dynamic: requires-dist
Dynamic: requires-python
Dynamic: summary
